lemmy/__init__.py
lemmy/admin.py
lemmy/auth.py
lemmy/comment.py
lemmy/community.py
lemmy/lemmy.py
lemmy/modlog.py
lemmy/post.py
lemmy/private_message.py
lemmy/search.py
lemmy/site.py
lemmy/user.py
Lemmy.py-0.0.2.dist-info/METADATA
Lemmy.py-0.0.2.dist-info/WHEEL
Lemmy.py-0.0.2.dist-info/top_level.txt
Lemmy.py-0.0.2.dist-info/RECORD
