Metadata-Version: 2.1
Name: Lemmy.py
Version: 0.0.2
Summary: Python wrapper for the Lemmy API
Author-email: retiolus <retiolus@tuta.io>
License: BSD-3-Clause
Keywords: wrapper,lemmy,api
Requires-Python: >=3.10
Requires-Dist: requests
Requires-Dist: loguru ; python_version > "3.10"
